sphinxcontrib_imagehelper-1.1.1-py2.7-nspkg.pth
sphinxcontrib/imagehelper/__init__.py
sphinxcontrib/imagehelper/directives.py
sphinxcontrib/imagehelper/imageext.py
sphinxcontrib/imagehelper/utils.py
sphinxcontrib_imagehelper-1.1.1.dist-info/DESCRIPTION.rst
sphinxcontrib_imagehelper-1.1.1.dist-info/METADATA
sphinxcontrib_imagehelper-1.1.1.dist-info/RECORD
sphinxcontrib_imagehelper-1.1.1.dist-info/WHEEL
sphinxcontrib_imagehelper-1.1.1.dist-info/metadata.json
sphinxcontrib_imagehelper-1.1.1.dist-info/namespace_packages.txt
sphinxcontrib_imagehelper-1.1.1.dist-info/top_level.txt
