Metadata-Version: 1.1
Name: sphinxcontrib-imagehelper
Version: 1.1.1
Summary: Sphinx extension helper about images
Home-page: https://github.com/tk0miya/sphinxcontrib-imagehelper
Author: Takeshi KOMIYA
Author-email: i.tkomiya@gmail.com
License: BSD
Platform: any
Classifier: Development Status :: 4 - Beta
Classifier: Environment :: Console
Classifier: Framework :: Sphinx :: Extension
Classifier: Intended Audience :: Developers
Classifier: License :: OSI Approved :: BSD License
Classifier: Operating System :: OS Independent
Classifier: Programming Language :: Python
Classifier: Programming Language :: Python :: 2.6
Classifier: Programming Language :: Python :: 2.7
Classifier: Programming Language :: Python :: 3.3
Classifier: Programming Language :: Python :: 3.4
Classifier: Topic :: Documentation
Classifier: Topic :: Documentation :: Sphinx
